LICENSE.md
MANIFEST.in
README.md
requirements.txt
setup.cfg
setup.py
MeteoGalicia_API.egg-info/PKG-INFO
MeteoGalicia_API.egg-info/SOURCES.txt
MeteoGalicia_API.egg-info/dependency_links.txt
MeteoGalicia_API.egg-info/not-zip-safe
MeteoGalicia_API.egg-info/requires.txt
MeteoGalicia_API.egg-info/top_level.txt
meteoGalicia_api.egg-info/PKG-INFO
meteoGalicia_api.egg-info/SOURCES.txt
meteoGalicia_api.egg-info/dependency_links.txt
meteoGalicia_api.egg-info/not-zip-safe
meteoGalicia_api.egg-info/requires.txt
meteoGalicia_api.egg-info/top_level.txt
meteogalicia_api/__init__.py
meteogalicia_api/const.py
meteogalicia_api/interface.py
tests/test_interface.py