Metadata-Version: 2.1
Name: meteoGalicia-api
Version: 0.1.2
Summary: Python library for get info from MeteoGalicia web service. MeteoGalicia is the meteorological agency for Galicia, Spain
Home-page: https://github.com/danieldiazi/meteogalicia-api
Author: danieldiazi
Author-email: dandiazde@gmail.com
License: GPLv3
Keywords: MeteoGalicia
Platform: any
Classifier: Development Status :: 5 - Production/Stable
Classifier: Intended Audience :: Developers
Classifier: License :: OSI Approved :: GNU General Public License v3 (GPLv3)
Classifier: Natural Language :: English
Classifier: Programming Language :: Python
Classifier: Programming Language :: Python :: 3
Classifier: Programming Language :: Python :: 3
Classifier: Programming Language :: Python :: 3.6
Classifier: Programming Language :: Python :: 3.7
Classifier: Programming Language :: Python :: 3.8
Classifier: Programming Language :: Python :: 3.9
Classifier: Programming Language :: Python :: 3.11
License-File: LICENSE.md
